prometry/__init__.py
prometry/geocalculator.py
prometry/pdbcontacts.py
prometry/pdbgeometry.py
prometry/pdbloader.py
prometry/pdbobject.py
prometry/pdbspace.py
prometry/reportmaker.py
prometry-1.0.1.dist-info/LICENSE
prometry-1.0.1.dist-info/METADATA
prometry-1.0.1.dist-info/WHEEL
prometry-1.0.1.dist-info/top_level.txt
prometry-1.0.1.dist-info/RECORD
