Metadata-Version: 2.1
Name: prometry
Version: 1.0.1
Summary: Library to calculate geometric parameters of protein structures including criteria searches.
Home-page: https://github.com/rae-gh/lib-prometry
Author: Rachel Alcraft
Author-email: rachelalcraft@gmail.com
Project-URL: Bug Tracker, https://github.com/rae-gh/lib-prometry/issues
Classifier: Programming Language :: Python :: 3
Classifier: License :: OSI Approved :: MIT License
Classifier: Operating System :: OS Independent
Requires-Python: >=3.6
License-File: LICENSE
